Metadata-Version: 2.1
Name: slik-wrangler
Version: 1.0.6
Summary: A data preprocessing and modeling tool
Home-page: https://github.com/AdesholaAfolabi/slik_python_package
Author: Adeshola Afolabi/Akinwande Komolafe
Author-email: afolabimkay@gmail.com
License: UNKNOWN
Platform: UNKNOWN
